ausdex/__init__.py
ausdex/dates.py
ausdex/files.py
ausdex/inflation.py
ausdex/location.py
ausdex/main.py
ausdex/viz.py
ausdex-1.2.0.dist-info/LICENSE
ausdex-1.2.0.dist-info/WHEEL
ausdex-1.2.0.dist-info/entry_points.txt
ausdex-1.2.0.dist-info/METADATA
ausdex-1.2.0.dist-info/RECORD
