Metadata-Version: 2.1
Name: ausdex
Version: 1.2.0
Summary: A Python package for adjusting Australian dollars for inflation
Home-page: https://github.com/rbturnbull/ausdex
License: Apache-2.0
Author: Robert Turnbull
Author-email: robert.turnbull@unimelb.edu.au
Requires-Python: >=3.8,<4.0.0
Classifier: License :: OSI Approved :: Apache Software License
Classifier: Programming Language :: Python :: 3
Classifier: Programming Language :: Python :: 3.8
Classifier: Programming Language :: Python :: 3.9
Classifier: Programming Language :: Python :: 3.10
Classifier: Programming Language :: Python :: 3.11
Requires-Dist: appdirs (>=1.4.4,<2.0.0)
Requires-Dist: cached-property (>=1.5.2,<2.0.0)
Requires-Dist: importlib-metadata (<4.3)
Requires-Dist: kaleido (==0.2.1)
Requires-Dist: modin (>=0.18.1,<0.19.0)
Requires-Dist: numpy (>=1.22.0,<2.0.0)
Requires-Dist: openpyxl (>=3.0.0,<4.0.0)
Requires-Dist: pandas (>=1.3.2,<2.0.0)
Requires-Dist: plotly (>=5.4.0,<6.0.0)
Requires-Dist: python-dateutil (>=2.8.2,<3.0.0)
Requires-Dist: typer (>=0.4.0,<0.5.0)
Requires-Dist: xlrd (>=2.0.1,<3.0.0)
Project-URL: Documentation, https://rbturnbull.github.io/ausdex/
Project-URL: Repository, https://github.com/rbturnbull/ausdex
